Metadata-Version: 2.1
Name: numpy
Version: 2.3.1
Summary: Fundamental package for array computing in Python
Author: Travis E. Oliphant et al.
Maintainer-Email: NumPy Developers <numpy-discussion@python.org>
License: Copyright (c) 2005-2025, NumPy Developers.
Classifier: Development Status :: 5 - Production/Stable
Classifier: Intended Audience :: Science/Research
Classifier: Intended Audience :: Developers
Classifier: License :: OSI Approved :: BSD License
Classifier: Programming Language :: C
Classifier: Programming Language :: Python
Classifier: Programming Language :: Python :: 3
Classifier: Programming Language :: Python :: 3.11
Classifier: Programming Language :: Python :: 3.12
Classifier: Programming Language :: Python :: 3.13
Classifier: Programming Language :: Python :: 3 :: Only
Classifier: Programming Language :: Python :: Implementation :: CPython
Classifier: Topic :: Software Development
Classifier: Topic :: Scientific/Engineering
Classifier: Typing :: Typed
Classifier: Operating System :: Microsoft :: Windows
Classifier: Operating System :: POSIX
Classifier: Operating System :: Unix
Classifier: Operating System :: MacOS
Project-URL: homepage, https://numpy.org
Project-URL: documentation, https://numpy.org/doc/
Project-URL: source, https://github.com/numpy/numpy
Project-URL: download, https://pypi.org/project/numpy/#files
Project-URL: tracker, https://github.com/numpy/numpy/issues
Project-URL: release notes, https://numpy.org/doc/stable/release
Requires-Python: >=3.11
